{
  "name": "My Project 2",
  "clearOwnership": {
    "isOwnershipExplicit": "Yes",
    "copyrightURL": "https://github.com/unicef/publicgoods-candidates"
  },
  "platformIndependence": {
    "mandatoryDepsCreateMoreRestrictions": "No"
  },
  "documentation": {
    "isDocumentationAvailable": "Yes",
    "documentationURL": "https://github.com/unicef/publicgoods-candidates"
  },
  "NonPII": {
    "collectsNonPII": "Yes",
    "checkNonPIIAccessMechanism": "Yes",
    "nonPIIAccessMechanism": "REST"
  },
  "privacy": {
    "isPrivacyCompliant": "Yes",
    "privacyComplianceList": [
      "GDPR"
    ],
    "adherenceSteps": [
      "Has a privacy policy made publicly available "
    ]
  },
  "standards": {
    "supportStandards": "Yes",
    "implementBestPractices": "Yes",
    "standardsList": [
      "REST"
    ],
    "evidenceStandardSupport": "https://github.com/unicef/publicgoods-candidates",
    "bestPracticesList": [
      "Principles for Digital Development"
    ]
  },
  "doNoHarm": {
    "preventHarm": {
      "stepsToPreventHarm": "Yes"
    },
    "dataPrivacySecurity": {
      "collectsPII": "Yes"
    },
    "inappropriateIllegalContent": {
      "collectStoreDistribute": "Yes"
    },
    "protectionFromHarassment": {
      "userInteraction": "Yes"
    }
  },
  "locations": {
    "developmentCountries": [
      "Angola"
    ],
    "deploymentCountries": [
      "Angola"
    ]
  }
}
